lightcnn_pytorch/__init__.py
lightcnn_pytorch/architectures.py
lightcnn_pytorch/model.py
lightcnn_pytorch/preprocessing.py
lightcnn_pytorch/utils.py
lightcnn_pytorch-0.5.0.dist-info/METADATA
lightcnn_pytorch-0.5.0.dist-info/WHEEL
lightcnn_pytorch-0.5.0.dist-info/top_level.txt
lightcnn_pytorch-0.5.0.dist-info/RECORD
